{
  "contributionUpstream": {
    "contribFile": {
      "dirname": "",
      "file": {
        "permalink": "https://wikifactory.com/files/RmlsZToyNzMxNTU="
      },
      "filename": "README.md",
      "isFolder": false
    },
    "files": [
      {
        "contribution": {
          "version": "9cb9ea98106760cec32cab71edbb5a6f16752d66"
        },
        "dirname": "",
        "file": null,
        "filename": "pieces"
      },
      {
        "contribution": {
          "version": "9cb9ea98106760cec32cab71edbb5a6f16752d66"
        },
        "dirname": "",
        "file": {
          "mimeType": "text/plain",
          "permalink": "https://wikifactory.com/files/RmlsZToyNTA3NTg="
        },
        "filename": "license.txt"
      },
      {
        "contribution": {
          "version": "9cb9ea98106760cec32cab71edbb5a6f16752d66"
        },
        "dirname": "pieces",
        "file": {
          "mimeType": "application/x-extension-fcstd",
          "permalink": "https://wikifactory.com/files/RmlsZToyNzMxNTM="
        },
        "filename": "corocottaV2.fcstd"
      },
      {
        "contribution": {
          "version": "9cb9ea98106760cec32cab71edbb5a6f16752d66"
        },
        "dirname": "pieces",
        "file": {
          "mimeType": "application/x-tgif",
          "permalink": "https://wikifactory.com/files/RmlsZToyNzMxNTI="
        },
        "filename": "corocottaV2_bed_slider.obj"
      },
      {
        "contribution": {
          "version": "9cb9ea98106760cec32cab71edbb5a6f16752d66"
        },
        "dirname": "pieces",
        "file": {
          "mimeType": "application/x-tgif",
          "permalink": "https://wikifactory.com/files/RmlsZToyNzMxNTE="
        },
        "filename": "corocottaV2_corner_body.obj"
      },
      {
        "contribution": {
          "version": "9cb9ea98106760cec32cab71edbb5a6f16752d66"
        },
        "dirname": "pieces",
        "file": {
          "mimeType": "application/x-tgif",
          "permalink": "https://wikifactory.com/files/RmlsZToyNzMxNTA="
        },
        "filename": "corocottaV2_corner_top.obj"
      },
      {
        "contribution": {
          "version": "9cb9ea98106760cec32cab71edbb5a6f16752d66"
        },
        "dirname": "pieces",
        "file": {
          "mimeType": "application/x-tgif",
          "permalink": "https://wikifactory.com/files/RmlsZToyNzMxNDk="
        },
        "filename": "corocottaV2_head_slider.obj"
      },
      {
        "contribution": {
          "version": "9cb9ea98106760cec32cab71edbb5a6f16752d66"
        },
        "dirname": "pieces",
        "file": {
          "mimeType": "image/png",
          "permalink": "https://wikifactory.com/files/RmlsZToyNzMxNDM="
        },
        "filename": "CorocottaV2_nombres_piezas.png"
      },
      {
        "contribution": {
          "version": "9cb9ea98106760cec32cab71edbb5a6f16752d66"
        },
        "dirname": "pieces",
        "file": {
          "mimeType": "application/x-tgif",
          "permalink": "https://wikifactory.com/files/RmlsZToyNzMxNDg="
        },
        "filename": "corocottaV2_pulley_side.obj"
      },
      {
        "contribution": {
          "version": "9cb9ea98106760cec32cab71edbb5a6f16752d66"
        },
        "dirname": "pieces",
        "file": {
          "mimeType": "application/x-tgif",
          "permalink": "https://wikifactory.com/files/RmlsZToyNzMxNDc="
        },
        "filename": "corocottaV2_slider.obj"
      },
      {
        "contribution": {
          "version": "9cb9ea98106760cec32cab71edbb5a6f16752d66"
        },
        "dirname": "pieces",
        "file": {
          "mimeType": "application/x-tgif",
          "permalink": "https://wikifactory.com/files/RmlsZToyNzMxNDY="
        },
        "filename": "corocottaV2_slider_plate.obj"
      },
      {
        "contribution": {
          "version": "9cb9ea98106760cec32cab71edbb5a6f16752d66"
        },
        "dirname": "pieces",
        "file": {
          "mimeType": "application/x-tgif",
          "permalink": "https://wikifactory.com/files/RmlsZToyNzMxNDQ="
        },
        "filename": "corocottaV2_z_motor_holder.obj"
      },
      {
        "contribution": {
          "version": "9cb9ea98106760cec32cab71edbb5a6f16752d66"
        },
        "dirname": "pieces",
        "file": {
          "mimeType": "application/x-tgif",
          "permalink": "https://wikifactory.com/files/RmlsZToyNzMxNDU="
        },
        "filename": "corocottaV2_zbar_holder.obj"
      },
      {
        "contribution": {
          "version": "9cb9ea98106760cec32cab71edbb5a6f16752d66"
        },
        "dirname": "",
        "file": {
          "mimeType": "text/markdown",
          "permalink": "https://wikifactory.com/files/RmlsZToyNzMxNTU="
        },
        "filename": "README.md"
      }
    ]
  },
  "creatorProfile": {
    "fullName": "Laurent Brunel",
    "username": "@lsbrunel"
  },
  "description": "<p>250mm\u00b3 cube like 3D printer, designed and made at FabLabSantander\u00ae, coreXY. Try to be as cheap as possible. </p><p></p>",
  "id": "UHJvamVjdDoyNTA3NTU=",
  "image": {
    "permalink": "https://wikifactory.com/files/RmlsZToyNzMyNzA="
  },
  "lastActivityAt": "2019-10-07T14:00:42.792787+00:00",
  "license": {
    "abreviation": "CC-BY-4.0",
    "name": "cc0",
    "title": "Creative Commons Attribution 4.0"
  },
  "name": "Corocotta",
  "slug": "corocotta",
  "space": {
    "content": {
      "__typename": "Content",
      "slug": "fablabsantander"
    },
    "id": "U3BhY2U6MTg3NjA="
  }
}